{
	"name": "app_1",
	"ownerId": "",
	"requestDate": "2014-11-03T13:01:37.921Z",
	"title": "",
	"applicationContext": [
		{
			"properties": [
				{
					"possibleValues": [],
					"name": "selectedItem",
					"value": ""
				}
			],
			"object": "menu"
		}
	],
	"github": {
		"token": "",
		"username": "",
		"repository": ""
	},
	"phonegap": {
		"token": "",
		"applicationId": ""
	},
	"requiredLibraries": [],
	"requiredStylesheets": [
		{
			"name": "_gc"
		},
		{
			"name": "_ext"
		}
	],
	"screenflow": [
		{
			"name": "Guest",
			"left": "85",
			"connections": [
				{
					"assertions": [],
					"name": "Home"
				}
			],
			"type": "http_guest",
			"top": "150"
		},
		{
			"name": "Home",
			"left": "330",
			"connections": [],
			"type": "screen",
			"top": "165"
		}
	],
	"start": "Home",
	"visibility": "visible",
	"platform": "web",
	"_id": "54577cb130b2a772155e55f5",
	"versioning": {
		"dreamface1": {
			"last_action": "1415019701",
			"status": "committed",
			"user": "admin"
		}
	}
}